settingsjson/__init__.py
settingsjson/settingsjson.py
settingsjson/test.py
settingsjson-1.0.2.dist-info/METADATA
settingsjson-1.0.2.dist-info/RECORD
settingsjson-1.0.2.dist-info/WHEEL
settingsjson-1.0.2.dist-info/top_level.txt
