Metadata-Version: 2.1
Name: settingsjson
Version: 1.0.2
Summary: getter simple setting json
Home-page: https://github.com/74th/settingsjson-py
Author: 74th
Author-email: site@j74th.com
License: UNKNOWN
Platform: UNKNOWN
Classifier: Programming Language :: Python :: 3
Classifier: Programming Language :: Python :: 2
Classifier: License :: OSI Approved :: MIT License
Classifier: Operating System :: OS Independent
